Metadata-Version: 1.1
Name: django-cache-magic
Version: 0.1.0
Summary: Django Cache Magic
Home-page: https://github.com/ntucker/django-cache-magic
Author: Nathaniel Tucker
Author-email: me@ntucker.me
License: BSD
Platform: UNKNOWN
Classifier: Development Status :: 4 - Beta
Classifier: Environment :: Web Environment
Classifier: Framework :: Django
Classifier: Intended Audience :: Developers
Classifier: License :: OSI Approved :: BSD License
Classifier: Operating System :: OS Independent
Classifier: Programming Language :: Python
Classifier: Programming Language :: Python :: 2
Classifier: Programming Language :: Python :: 2.7
